msisensor_rna/detection.py
msisensor_rna/msisensor_rna.py
msisensor_rna/paras.py
msisensor_rna/show.py
msisensor_rna/train.py
msisensor_rna/units.py
msisensor_rna-0.1.5.dist-info/LICENSE
msisensor_rna-0.1.5.dist-info/METADATA
msisensor_rna-0.1.5.dist-info/WHEEL
msisensor_rna-0.1.5.dist-info/entry_points.txt
msisensor_rna-0.1.5.dist-info/top_level.txt
msisensor_rna-0.1.5.dist-info/RECORD
