Metadata-Version: 2.1
Name: msisensor-rna
Version: 0.1.5
Summary: msisensor-rna Microsatellite Instability (MSI) detection with RNA sequencing data.
Home-page: https://github.com/xjtu-omics/msisensor-rna
Author: Peng Jia, Xuanhao Yang et al.
Author-email: pengjia@stu.xjtu.edu.cn
License: Custom License
Keywords: Microsatellite instability,RNA-seq,Immunotherapy,Tumor only
Platform: UNKNOWN
Requires-Python: >=3.6
License-File: LICENSE
Requires-Dist: pandas (>=1.0)
Requires-Dist: numpy (>=1.16)
Requires-Dist: scikit-learn (>=0.24)
Requires-Dist: imbalanced-learn (>=0.8.0)
